{
  "3.0.0": {
    "requestUrls": [
      {
        "type": "服务商接入",
        "url": "https://open.youzan.com/api/oauthentry/youzan.retail.open.spu/3.0.0/get"
      },
      {
        "type": "商家自有接入",
        "url": "https://open.youzan.com/api/entry/youzan.retail.open.spu/3.0.0/get"
      }
    ],
    "requestParams": [
      {
        "name": "retail_source",
        "type": "String",
        "example": "",
        "defaultValue": "",
        "isRequired": "是",
        "desc": "零售调用来源(调用方和有赞约定的值)",
        "isStruct": false,
        "structUrl": null,
        "struct": null
      },
      {
        "name": "spu_code",
        "type": "String",
        "example": "",
        "defaultValue": "",
        "isRequired": "是",
        "desc": "商品编码",
        "isStruct": false,
        "structUrl": null,
        "struct": null
      },
      {
        "name": "warehouse_code",
        "type": "String",
        "example": "",
        "defaultValue": "",
        "isRequired": "否",
        "desc": "仓库编码",
        "isStruct": false,
        "structUrl": null,
        "struct": null
      }
    ],
    "responseParams": [
      {
        "name": "response",
        "type": "OpenSpuDTO",
        "isRequired": "否",
        "desc": "商品信息",
        "isStruct": true,
        "structUrl": "/web/meta/OpenSpuDTO",
        "struct": {
          "name": "response",
          "type": "OpenSpuDTO",
          "isNeed": "true",
          "desc": "商品信息",
          "defaultValue": null,
          "example": null,
          "isStruct": true,
          "children": [
            {
              "name": "category_id",
              "type": "String",
              "isNeed": null,
              "desc": "类目ID",
              "defaultValue": null,
              "example": null,
              "isStruct": false,
              "children": []
            },
            {
              "name": "category_name",
              "type": "String",
              "isNeed": null,
              "desc": "类目名称",
              "defaultValue": null,
              "example": null,
              "isStruct": false,
              "children": []
            },
            {
              "name": "product_name",
              "type": "String",
              "isNeed": null,
              "desc": "商品名称",
              "defaultValue": null,
              "example": null,
              "isStruct": false,
              "children": []
            },
            {
              "name": "unit",
              "type": "String",
              "isNeed": null,
              "desc": "单位",
              "defaultValue": null,
              "example": null,
              "isStruct": false,
              "children": []
            },
            {
              "name": "spu_no",
              "type": "String",
              "isNeed": null,
              "desc": "spu条码",
              "defaultValue": null,
              "example": null,
              "isStruct": false,
              "children": []
            },
            {
              "name": "bar_codes",
              "type": "String[]",
              "isNeed": null,
              "desc": "一品多码",
              "defaultValue": null,
              "example": null,
              "isStruct": false,
              "children": []
            },
            {
              "name": "sell_channels",
              "type": "Number[]",
              "isNeed": null,
              "desc": "销售渠道\n2=门店,4=网店",
              "defaultValue": null,
              "example": null,
              "isStruct": false,
              "children": []
            },
            {
              "name": "create_time",
              "type": "String",
              "isNeed": null,
              "desc": "创建时间",
              "defaultValue": null,
              "example": null,
              "isStruct": false,
              "children": []
            },
            {
              "name": "update_time",
              "type": "String",
              "isNeed": null,
              "desc": "修改时间",
              "defaultValue": null,
              "example": null,
              "isStruct": false,
              "children": []
            },
            {
              "name": "skus",
              "type": "OpenBaseSkuDTO[]",
              "isNeed": null,
              "desc": "商品SKU基础数据",
              "defaultValue": null,
              "example": null,
              "isStruct": true,
              "children": [
                {
                  "name": "category_id",
                  "type": "String",
                  "isNeed": null,
                  "desc": "类目id",
                  "defaultValue": null,
                  "example": null,
                  "isStruct": false,
                  "children": []
                },
                {
                  "name": "category_name",
                  "type": "String",
                  "isNeed": null,
                  "desc": "类目名称",
                  "defaultValue": null,
                  "example": null,
                  "isStruct": false,
                  "children": []
                },
                {
                  "name": "product_name",
                  "type": "String",
                  "isNeed": null,
                  "desc": "商品名称",
                  "defaultValue": null,
                  "example": null,
                  "isStruct": false,
                  "children": []
                },
                {
                  "name": "specifications",
                  "type": "String",
                  "isNeed": null,
                  "desc": "规格",
                  "defaultValue": null,
                  "example": null,
                  "isStruct": false,
                  "children": []
                },
                {
                  "name": "unit",
                  "type": "String",
                  "isNeed": null,
                  "desc": "单位",
                  "defaultValue": null,
                  "example": null,
                  "isStruct": false,
                  "children": []
                },
                {
                  "name": "sku_no",
                  "type": "String",
                  "isNeed": null,
                  "desc": "sku条码",
                  "defaultValue": null,
                  "example": null,
                  "isStruct": false,
                  "children": []
                },
                {
                  "name": "sku_code",
                  "type": "String",
                  "isNeed": null,
                  "desc": "sku编码",
                  "defaultValue": null,
                  "example": null,
                  "isStruct": false,
                  "children": []
                },
                {
                  "name": "bar_codes",
                  "type": "String[]",
                  "isNeed": null,
                  "desc": "一品多码",
                  "defaultValue": null,
                  "example": null,
                  "isStruct": false,
                  "children": []
                },
                {
                  "name": "retail_price",
                  "type": "String",
                  "isNeed": null,
                  "desc": "建议零售价",
                  "defaultValue": null,
                  "example": null,
                  "isStruct": false,
                  "children": []
                },
                {
                  "name": "output_tax_rate",
                  "type": "String",
                  "isNeed": null,
                  "desc": "销项税率",
                  "defaultValue": null,
                  "example": null,
                  "isStruct": false,
                  "children": []
                },
                {
                  "name": "input_tax_tate",
                  "type": "String",
                  "isNeed": null,
                  "desc": "进项税率",
                  "defaultValue": null,
                  "example": null,
                  "isStruct": false,
                  "children": []
                },
                {
                  "name": "create_time",
                  "type": "String",
                  "isNeed": null,
                  "desc": "创建日期",
                  "defaultValue": null,
                  "example": null,
                  "isStruct": false,
                  "children": []
                },
                {
                  "name": "update_time",
                  "type": "String",
                  "isNeed": null,
                  "desc": "更新日期",
                  "defaultValue": null,
                  "example": null,
                  "isStruct": false,
                  "children": []
                }
              ]
            },
            {
              "name": "spu_code",
              "type": "String",
              "isNeed": null,
              "desc": "spu编码",
              "defaultValue": null,
              "example": null,
              "isStruct": false,
              "children": []
            },
            {
              "name": "photo_url",
              "type": "String",
              "isNeed": null,
              "desc": "图片地址",
              "defaultValue": null,
              "example": null,
              "isStruct": false,
              "children": []
            }
          ]
        }
      }
    ],
    "requestDemos": [
      {
        "lang": "java",
        "code": "YZClient client = new DefaultYZClient(new Token(\"token\")); //new Sign(appKey, appSecret)\nYouzanRetailOpenSpuGetParams youzanRetailOpenSpuGetParams = new YouzanRetailOpenSpuGetParams();\n\nyouzanRetailOpenSpuGetParams.setRetailSource(\"GUANYIYUN\");\nyouzanRetailOpenSpuGetParams.setSpuCode(\"BM9613847615\");\nyouzanRetailOpenSpuGetParams.setWarehouseCode(\"\");\n\nYouzanRetailOpenSpuGet youzanRetailOpenSpuGet = new YouzanRetailOpenSpuGet();\nyouzanRetailOpenSpuGet.setAPIParams(youzanRetailOpenSpuGetParams);\nYouzanRetailOpenSpuGetResult result = client.invoke(youzanRetailOpenSpuGet);"
      },
      {
        "lang": "csharp",
        "code": "Auth auth = new Token(\"xxx\"); // Auth auth = new Sign(\"app_id\", \"app_secret\");\n\nYZClient yzClient = new DefaultYZClient(auth);\nDictionary<string, object> dict = new System.Collections.Generic.Dictionary<string, object>();\ndict.Add(\"retail_source\", \"GUANYIYUN\");\ndict.Add(\"spu_code\", \"BM9613847615\");\ndict.Add(\"warehouse_code\", \"\");\n\n\nvar result = yzClient.Invoke(\"youzan.retail.open.spu.get\", \"3.0.0\", \"POST\", dict, null);\nConsole.WriteLine(result);\n"
      },
      {
        "lang": "php",
        "code": "<?php\nrequire_once __DIR__ . '/lib/YZTokenClient.php';\n\n$token = 'fill your token';//请填入商家授权后获取的access_token\n$client = new YZTokenClient($token);\n\n$method = 'youzan.retail.open.spu.get'; //要调用的api名称\n$api_version = '3.0.0'; //要调用的api版本号\n\n$my_params = [\n    'retail_source' => 'GUANYIYUN',\n    'spu_code' => 'BM9613847615',\n    'warehouse_code' => '',\n];\n\n$my_files = [\n];\n\necho '<pre>';\nvar_dump(\n    $client->post($method, $api_version, $my_params, $my_files)\n);\necho '</pre>';\n"
      },
      {
        "lang": "python",
        "code": "token = auth.Token(token='token') #auth.Sign(app_id='app_id', app_secret='app_secret')\n\nclient = YZClient(token)\n\nparams={}\n\nparams['retail_source']=\"GUANYIYUN\"\nparams['spu_code']=\"BM9613847615\"\nparams['warehouse_code']=\"\"\n\nfiles=[]\n\nprint client.invoke('youzan.retail.open.spu.get', '3.0.0', 'POST', params=params, files=files)\n"
      },
      {
        "lang": "nodejs",
        "code": "var YZClient = require('yz-open-sdk-nodejs');\nvar Token = require('./node_modules/yz-open-sdk-nodejs/Token');\n\nvar YZClient = new YZClient(new Token('xxxx')); // var YZClient = new YZClient(new Sign('app_id', 'app_secret'));\n\nparams={};\n\nparams['retail_source']=\"GUANYIYUN\";\nparams['spu_code']=\"BM9613847615\";\nparams['warehouse_code']=\"\";\n\n\nvar promise = YZClient.invoke('youzan.retail.open.spu.get', '3.0.0', 'POST', params, undefined);\n\npromise.then(function(resp) {\n    console.log('resp: ' + resp.body);\n    var data = JSON.parse(resp.body);\n    console.log(data);\n}, function(err) {\n    console.log('err: ' + err);\n}, function(prog) {\n    console.log('prog: ' + prog);\n});\n"
      }
    ],
    "errorCodes": [
      {
        "errorCode": "234008004",
        "errorDesc": "查询商品失败(spu)",
        "solution": "重试，仍然失败，联系有赞技术支持"
      }
    ],
    "responseDemo": "{\"response\":{\"skus\":[{\"avg_stock_in_cost\":\"0\",\"category_name\":\"未分类\",\"create_time\":\"2018-12-19 09:55:17\",\"stock_num\":\"0\",\"sku_id\":93574374,\"sell_stock_num\":\"0\",\"specifications\":\"粉\",\"product_name\":\"小盒侠保温杯-500ml\",\"retail_price\":\"70\",\"update_time\":\"2018-12-24 13:47:56\",\"unit\":\"件\",\"bar_codes\":[],\"sku_no\":\"6933397711522\",\"category_id\":\"672902\",\"sku_code\":\"BM961384764693574374\",\"last_stock_in_cost\":\"0\"},{\"avg_stock_in_cost\":\"0\",\"category_name\":\"未分类\",\"create_time\":\"2018-12-19 09:55:17\",\"stock_num\":\"0\",\"sku_id\":93574375,\"sell_stock_num\":\"0\",\"specifications\":\"蓝\",\"product_name\":\"小盒侠保温杯-500ml\",\"retail_price\":\"2\",\"update_time\":\"2018-12-24 13:47:56\",\"unit\":\"件\",\"bar_codes\":[],\"sku_no\":\"6933397711515\",\"category_id\":\"672902\",\"sku_code\":\"BM961384765593574375\",\"last_stock_in_cost\":\"0\"},{\"avg_stock_in_cost\":\"0\",\"category_name\":\"未分类\",\"create_time\":\"2018-12-19 09:55:17\",\"stock_num\":\"0\",\"sku_id\":93574376,\"sell_stock_num\":\"0\",\"specifications\":\"白\",\"product_name\":\"小盒侠保温杯-500ml\",\"retail_price\":\"70\",\"update_time\":\"2018-12-24 13:47:56\",\"unit\":\"件\",\"bar_codes\":[\"9876543210\"],\"sku_no\":\"6933397711539\",\"category_id\":\"672902\",\"sku_code\":\"BM961384765893574376\",\"last_stock_in_cost\":\"0\"}],\"category_name\":\"未分类\",\"create_time\":\"2018-12-19 09:55:17\",\"multi_units_spu\":0,\"spu_code\":\"BM9613847615\",\"is_non_spec\":false,\"specifications\":\"粉\",\"product_name\":\"小盒侠保温杯-500ml\",\"unit_settings\":[],\"sell_channels\":[4],\"update_time\":\"2018-12-24 13:55:34\",\"unit\":\"件\",\"bar_codes\":[],\"category_id\":\"672902\",\"spu_no\":\"P181219262204961\",\"spu_id\":96138476,\"spec_define_tuple\":\"[{\\\"key\\\":{\\\"k\\\":\\\"颜色\\\",\\\"kId\\\":1},\\\"values\\\":[{\\\"v\\\":\\\"粉\\\",\\\"vId\\\":156},{\\\"v\\\":\\\"蓝\\\",\\\"vId\\\":157},{\\\"v\\\":\\\"白\\\",\\\"vId\\\":37}]}]\"}}",
    "errorResponseDemo": "{\"error_response\":{\"msg\":\"查询商品失败(spu)\",\"code\":234008004}}"
  },
  "name": "get",
  "ids": [
    11169
  ],
  "scenarios": "获取商品信息详情",
  "version": [
    "3.0.0"
  ],
  "desc": "获取商品信息详情"
}
