{
  "3.0.0": {
    "requestUrls": [
      {
        "type": "服务商接入",
        "url": "https://open.youzan.com/api/oauthentry/youzan.logistics.fee/3.0.0/get"
      },
      {
        "type": "商家自有接入",
        "url": "https://open.youzan.com/api/entry/youzan.logistics.fee/3.0.0/get"
      }
    ],
    "requestParams": [
      {
        "name": "city_name",
        "type": "String",
        "example": "",
        "defaultValue": "",
        "isRequired": "是",
        "desc": "城市名称",
        "isStruct": false,
        "structUrl": null,
        "struct": null
      },
      {
        "name": "county_name",
        "type": "String",
        "example": "",
        "defaultValue": "",
        "isRequired": "是",
        "desc": "区县名称",
        "isStruct": false,
        "structUrl": null,
        "struct": null
      },
      {
        "name": "item_param_list",
        "type": "String",
        "example": "",
        "defaultValue": "",
        "isRequired": "是",
        "desc": "交易商品列表",
        "isStruct": false,
        "structUrl": null,
        "struct": null
      },
      {
        "name": "order_no",
        "type": "String",
        "example": "",
        "defaultValue": "",
        "isRequired": "是",
        "desc": "订单号",
        "isStruct": false,
        "structUrl": null,
        "struct": null
      },
      {
        "name": "province_name",
        "type": "String",
        "example": "",
        "defaultValue": "",
        "isRequired": "是",
        "desc": "省份名称",
        "isStruct": false,
        "structUrl": null,
        "struct": null
      }
    ],
    "responseParams": [
      {
        "name": "countyId",
        "type": "Number",
        "isRequired": "否",
        "desc": "区县id",
        "isStruct": false,
        "structUrl": null,
        "struct": {
          "name": "countyId",
          "type": "Number",
          "isNeed": "false",
          "desc": "区县id",
          "defaultValue": null,
          "example": "330102",
          "isStruct": false,
          "children": null
        }
      },
      {
        "name": "totalPostage",
        "type": "Number",
        "isRequired": "否",
        "desc": "订单总快递费",
        "isStruct": false,
        "structUrl": null,
        "struct": {
          "name": "totalPostage",
          "type": "Number",
          "isNeed": "false",
          "desc": "订单总快递费",
          "defaultValue": null,
          "example": "1000",
          "isStruct": false,
          "children": null
        }
      },
      {
        "name": "itemsPostage",
        "type": "Map",
        "isRequired": "否",
        "desc": "商品运费详情 key=itemId, value=postage",
        "isStruct": true,
        "structUrl": "/web/meta/Map",
        "struct": {
          "name": "itemsPostage",
          "type": "Map",
          "isNeed": "false",
          "desc": "商品运费详情 key=itemId, value=postage",
          "defaultValue": null,
          "example": "{\"1\":3000}",
          "isStruct": true,
          "children": [
            {
              "name": "skuId",
              "type": "Number",
              "isNeed": null,
              "desc": "待更新商品id",
              "defaultValue": null,
              "example": null,
              "isStruct": false,
              "children": []
            },
            {
              "name": "result",
              "type": "Boolean",
              "isNeed": null,
              "desc": "是否更新成功",
              "defaultValue": null,
              "example": null,
              "isStruct": false,
              "children": []
            }
          ]
        }
      }
    ],
    "requestDemos": [
      {
        "lang": "java",
        "code": "YZClient client = new DefaultYZClient(new Token(\"token\")); //new Sign(appKey, appSecret)\nYouzanLogisticsFeeGetParams youzanLogisticsFeeGetParams = new YouzanLogisticsFeeGetParams();\n\nyouzanLogisticsFeeGetParams.setCityName(\"杭州市\");\nyouzanLogisticsFeeGetParams.setCountyName(\"上城区\");\nyouzanLogisticsFeeGetParams.setItemParamList(\"[{\"amount\":1,\"itemId\":1,\"itemType\":0,\"skuId\":1,\"supplyKdtId\":0,\"templateId\":1,\"unifiedPostage\":1}]\");\nyouzanLogisticsFeeGetParams.setOrderNo(\"E20170410113933101552932\");\nyouzanLogisticsFeeGetParams.setProvinceName(\"浙江省\");\n\nYouzanLogisticsFeeGet youzanLogisticsFeeGet = new YouzanLogisticsFeeGet();\nyouzanLogisticsFeeGet.setAPIParams(youzanLogisticsFeeGetParams);\nYouzanLogisticsFeeGetResult result = client.invoke(youzanLogisticsFeeGet);"
      }
    ],
    "errorCodes": null,
    "responseDemo": "{\"response\":{\"countyId\":330102,\"itemsPostage\":{\"1\":3000},\"totalPostage\":3000}}",
    "errorResponseDemo": "{\"error_response\":{\"code\":120001003,\"message\":\"很抱歉，该地区暂不支持配送\"}}"
  },
  "name": "get",
  "ids": [
    8078
  ],
  "scenarios": "运费计算，返回结果只需关注 totalPostage 总快递费。",
  "version": [
    "3.0.0"
  ],
  "desc": "运费计算"
}
