{
  "3.0.0": {
    "requestUrls": [
      {
        "type": "服务商接入",
        "url": "https://open.youzan.com/api/oauthentry/youzan.pay.qrcodes/3.0.0/get"
      },
      {
        "type": "商家自有接入",
        "url": "https://open.youzan.com/api/entry/youzan.pay.qrcodes/3.0.0/get"
      }
    ],
    "requestParams": [
      {
        "name": "ignore_qrcode",
        "type": "String",
        "example": "",
        "defaultValue": "0",
        "isRequired": "否",
        "desc": "是否不返回二维码图片，1即不返回qr_code数据",
        "isStruct": false,
        "structUrl": null,
        "struct": null
      },
      {
        "name": "label_ids",
        "type": "String",
        "example": "",
        "defaultValue": "",
        "isRequired": "否",
        "desc": "标签 json格式字符串,例如:[1,2],表示有两个标签",
        "isStruct": false,
        "structUrl": null,
        "struct": null
      },
      {
        "name": "page_no",
        "type": "Number",
        "example": "",
        "defaultValue": "1",
        "isRequired": "否",
        "desc": "当前页码",
        "isStruct": false,
        "structUrl": null,
        "struct": null
      },
      {
        "name": "page_size",
        "type": "Number",
        "example": "",
        "defaultValue": "20",
        "isRequired": "否",
        "desc": "每页条数",
        "isStruct": false,
        "structUrl": null,
        "struct": null
      },
      {
        "name": "qr_type",
        "type": "String",
        "example": "",
        "defaultValue": "QR_TYPE_NOLIMIT",
        "isRequired": "否",
        "desc": "二维码类型，不指定类型则全部返回",
        "isStruct": false,
        "structUrl": null,
        "struct": null
      },
      {
        "name": "shop_id",
        "type": "String",
        "example": "",
        "defaultValue": "",
        "isRequired": "否",
        "desc": "网点编号",
        "isStruct": false,
        "structUrl": null,
        "struct": null
      },
      {
        "name": "shop_type",
        "type": "String",
        "example": "",
        "defaultValue": "",
        "isRequired": "否",
        "desc": "网点类型",
        "isStruct": false,
        "structUrl": null,
        "struct": null
      }
    ],
    "responseParams": [
      {
        "name": "total_results",
        "type": "QrTotalResult",
        "isRequired": "否",
        "desc": "搜索到符合条件的结果总数",
        "isStruct": true,
        "structUrl": "/web/meta/QrTotalResult",
        "struct": {
          "name": "total_results",
          "type": "QrTotalResult",
          "isNeed": "true",
          "desc": "搜索到符合条件的结果总数",
          "defaultValue": null,
          "example": null,
          "isStruct": true,
          "children": [
            {
              "name": "total",
              "type": "Integer",
              "isNeed": null,
              "desc": "结果总数",
              "defaultValue": null,
              "example": null,
              "isStruct": false,
              "children": []
            }
          ]
        }
      },
      {
        "name": "qrcodes",
        "type": "TradeCashierQrcode[]",
        "isRequired": "否",
        "desc": "二维码生成记录,包含is_discount(是否有折扣)、activityInfo(折扣详情)，如果没有折扣则is_discount、activityInfo两个字段不返回",
        "isStruct": true,
        "structUrl": "/web/meta/TradeCashierQrcode",
        "struct": {
          "name": "qrcodes",
          "type": "TradeCashierQrcode[]",
          "isNeed": "true",
          "desc": "二维码生成记录,包含is_discount(是否有折扣)、activityInfo(折扣详情)，如果没有折扣则is_discount、activityInfo两个字段不返回",
          "defaultValue": null,
          "example": null,
          "isStruct": true,
          "children": [
            {
              "name": "qr_name",
              "type": "String",
              "isNeed": null,
              "desc": "收款名称",
              "defaultValue": null,
              "example": null,
              "isStruct": false,
              "children": []
            },
            {
              "name": "qr_price",
              "type": "Price",
              "isNeed": null,
              "desc": "收款金额。精确到2位小数；单位：元。",
              "defaultValue": null,
              "example": null,
              "isStruct": false,
              "children": []
            },
            {
              "name": "qr_code",
              "type": "String",
              "isNeed": null,
              "desc": "收款码编码",
              "defaultValue": null,
              "example": null,
              "isStruct": false,
              "children": []
            },
            {
              "name": "activityInfo",
              "type": "String",
              "isNeed": null,
              "desc": "收款码当前关联优惠信息。",
              "defaultValue": null,
              "example": null,
              "isStruct": false,
              "children": []
            },
            {
              "name": "qr_source",
              "type": "String",
              "isNeed": null,
              "desc": "收款码创建类型标记。<br>类型有：<br>INSIDE（内部创建）<br>OUTSIDE（外部创建）",
              "defaultValue": null,
              "example": null,
              "isStruct": false,
              "children": []
            },
            {
              "name": "qr_type",
              "type": "String",
              "isNeed": null,
              "desc": "收款码类型。<br>类型有：<br>QR_TYPE_FIXED（收款码和店铺绑定并且可多次支付）<br>QR_TYPE_NOLIMIT（收款码可多次支付）<br>QR_TYPE_DYNAMIC（收款码只能被支付一次）",
              "defaultValue": null,
              "example": null,
              "isStruct": false,
              "children": []
            },
            {
              "name": "qr_id",
              "type": "String",
              "isNeed": null,
              "desc": "收款码编号",
              "defaultValue": null,
              "example": null,
              "isStruct": false,
              "children": []
            },
            {
              "name": "qr_url",
              "type": "String",
              "isNeed": null,
              "desc": "可以访问的支付页URL",
              "defaultValue": null,
              "example": null,
              "isStruct": false,
              "children": []
            },
            {
              "name": "qr_created_time",
              "type": "String",
              "isNeed": null,
              "desc": "收款码创建日期",
              "defaultValue": null,
              "example": null,
              "isStruct": false,
              "children": []
            }
          ]
        }
      }
    ],
    "requestDemos": null,
    "errorCodes": null,
    "responseDemo": null,
    "errorResponseDemo": null
  },
  "name": "get",
  "ids": [
    8110
  ],
  "scenarios": "获取收款二维码生成记录列表",
  "version": [
    "3.0.0"
  ],
  "desc": "获取收款二维码生成记录列表"
}
