{"3.0.0":{"requestUrls":[{"type":"服务商接入","url":"https://open.youzan.com/api/oauthentry/youzan.mei.memberlevel/3.0.0/update"},{"type":"商家自有接入","url":"https://open.youzan.com/api/entry/youzan.mei.memberlevel/3.0.0/update"}],"requestParams":[{"name":"level_id","type":"Number","example":"","defaultValue":"","isRequired":"是","desc":"要更新的等级的等级id","isStruct":false,"structUrl":null,"struct":null},{"name":"level_name","type":"String","example":"","defaultValue":"","isRequired":"是","desc":"等级名称","isStruct":false,"structUrl":null,"struct":null},{"name":"level_right_settings","type":"MeiLevelRightSetting[]","example":"","defaultValue":"","isRequired":"是","desc":"权益列表","isStruct":true,"structUrl":"/web/apiParamStruct/MeiLevelRightSetting","struct":{"name":"MeiLevelRightSetting[]","type":"MeiLevelRightSetting[]","isStruct":true,"desc":"","example":null,"creator":null,"children":[{"name":"enable","type":"Number","isStruct":false,"desc":"是否启用。0 不启用 1启用","example":null,"creator":null,"children":[]},{"name":"level_right_type","type":"Number","isStruct":false,"desc":"权益分类。1 通用类权益；2 折扣权益；3 自定义权益","example":null,"creator":null,"children":[]},{"name":"member_right_type","type":"Number","isStruct":false,"desc":"会员权益分类。200 \"等级商品折扣\"；201 \"等级服务折扣\"；202  \"等级产品包邮\"；203  \"等级生日祝福\"；204 \"等级自定义权限\"","example":null,"creator":null,"children":[]},{"name":"name","type":"String","isStruct":false,"desc":"权益名称，只有自定义权益需要使用","example":null,"creator":null,"children":[]},{"name":"value","type":"Number","isStruct":false,"desc":"权益的值，如果权益有变化的值，可以通过这个字段指定，比如折扣","example":null,"creator":null,"children":[]}]}},{"name":"level_value","type":"Number","example":"","defaultValue":"","isRequired":"是","desc":"成长值","isStruct":false,"structUrl":null,"struct":null},{"name":"m_token","type":"String","example":"","defaultValue":"","isRequired":"是","desc":"美业token","isStruct":false,"structUrl":null,"struct":null}],"responseParams":[{"name":"is_success","type":"Boolean","isRequired":"否","desc":"更新结果","isStruct":false,"structUrl":null,"struct":{"name":"is_success","type":"Boolean","isNeed":"true","desc":"更新结果","defaultValue":null,"example":null,"isStruct":false,"children":null}}],"requestDemos":null,"errorCodes":null,"responseDemo":null,"errorResponseDemo":"{\"error_response\":{\"msg\":\"抱歉, 服务器开了个小差\",\"code\":230100000}}"},"name":"update","ids":[10295],"scenarios":"更新一个会员等级的信息","version":["3.0.0"],"desc":"更新一个会员等级的信息"}