{"3.0.0":{"requestUrls":[{"type":"服务商接入","url":"https://open.youzan.com/api/oauthentry/youzan.mei.order/3.0.0/create"},{"type":"商家自有接入","url":"https://open.youzan.com/api/entry/youzan.mei.order/3.0.0/create"}],"requestParams":[{"name":"buyer_gender","type":"Number","example":"","defaultValue":"","isRequired":"否","desc":"买家性别","isStruct":false,"structUrl":null,"struct":null},{"name":"buyer_mobile","type":"String","example":"","defaultValue":"","isRequired":"否","desc":"买家手机号","isStruct":false,"structUrl":null,"struct":null},{"name":"buyer_name","type":"String","example":"","defaultValue":"","isRequired":"否","desc":"买家姓名","isStruct":false,"structUrl":null,"struct":null},{"name":"buyer_yz_uid","type":"Number","example":"","defaultValue":"","isRequired":"否","desc":"买家id，如果是预约单转开单的，需要填入该参数，传对应预约人的ID","isStruct":false,"structUrl":null,"struct":null},{"name":"dept_id","type":"String","example":"","defaultValue":"","isRequired":"否","desc":"分店id，只有在总店开单的时候需要传入，并且只能出入分店id","isStruct":false,"structUrl":null,"struct":null},{"name":"m_token","type":"String","example":"","defaultValue":"","isRequired":"是","desc":"美业token","isStruct":false,"structUrl":null,"struct":null},{"name":"order_gift_items","type":"OrderGiftItem[]","example":"","defaultValue":"","isRequired":"否","desc":"赠送列表","isStruct":true,"structUrl":"/web/apiParamStruct/OrderGiftItem","struct":{"name":"OrderGiftItem[]","type":"OrderGiftItem[]","isStruct":true,"desc":"","example":null,"creator":null,"children":[{"name":"gift_item_term_time","type":"Number","isStruct":false,"desc":"权益有效期时间（giftItemTermTime，xxxx前有效），0-永久有效, 单位毫秒","example":null,"creator":null,"children":[]},{"name":"gift_item_unique","type":"String","isStruct":false,"desc":"赠送项目唯一值, 如：商品id","example":null,"creator":null,"children":[]},{"name":"gift_item_value","type":"Number","isStruct":false,"desc":"赠送权益值（giftItemValue, 赠送次数/数量）","example":null,"creator":null,"children":[]},{"name":"gift_type","type":"Number","isStruct":false,"desc":"赠送类型（giftType,1-次数/2-折扣/3-余额/4-积分/5-券/6-会员卡/7-服务/8-产品）","example":null,"creator":null,"children":[]}]}},{"name":"order_items","type":"OrderItemRequest[]","example":"","defaultValue":"","isRequired":"是","desc":"订单项列表","isStruct":true,"structUrl":"/web/apiParamStruct/OrderItemRequest","struct":{"name":"OrderItemRequest[]","type":"OrderItemRequest[]","isStruct":true,"desc":"","example":null,"creator":null,"children":[{"name":"goods_id","type":"Number","isStruct":false,"desc":"商品id","example":null,"creator":null,"children":[]},{"name":"index","type":"Number","isStruct":false,"desc":"订单项位置，更新订单项时需传入","example":null,"creator":null,"children":[]},{"name":"is_pay","type":"Number","isStruct":false,"desc":"是否已支付","example":null,"creator":null,"children":[]},{"name":"item_alias","type":"String","isStruct":false,"desc":"订单项别名","example":null,"creator":null,"children":[]},{"name":"item_id","type":"Number","isStruct":false,"desc":"订单项id","example":null,"creator":null,"children":[]},{"name":"item_type","type":"Number","isStruct":false,"desc":"订单项类型。1, \"服务\"  2, \"次卡\"  3, \"折扣卡\"  4, \"充值卡\"  5, \"充值\"  6, \"台卡二维码收款\"  7, \"直接收款\"  8, \"实物商品\"  9, \"余额充值\"","example":null,"creator":null,"children":[]},{"name":"num","type":"Number","isStruct":false,"desc":"数量","example":null,"creator":null,"children":[]},{"name":"origin_price","type":"Number","isStruct":false,"desc":"原始价格","example":null,"creator":null,"children":[]},{"name":"promotion_card_no","type":"String","isStruct":false,"desc":"优惠卡号","example":null,"creator":null,"children":[]},{"name":"promotion_id","type":"Number","isStruct":false,"desc":"优惠id","example":null,"creator":null,"children":[]},{"name":"promotion_name","type":"String","isStruct":false,"desc":"优惠名称","example":null,"creator":null,"children":[]},{"name":"promotion_price","type":"Number","isStruct":false,"desc":"优惠的价格","example":null,"creator":null,"children":[]},{"name":"promotion_type","type":"Number","isStruct":false,"desc":"0, \"无优惠\" 1, \"次卡\" 2, \"折扣值\" 3, \"预付已付款\" 5, \"导入权益次数\" 6, \"赠送权益次数\" 7, \"导入权益折扣\" 8, \"赠送权益折扣\" 11, \"产品折扣（会员特权）\" 21, \"服务折扣（会员特权）\" 30, \"包邮\", \"等级权益包邮\" 31, \"抹零\", \"抹零\" 40, \"手动减价\", \"手动减价\" 51, \"减价优惠券\", \"优惠券\" 52, \"折扣优惠券\", \"优惠券\" 100, \"体验价\", \"体验价优惠\" 101, \"拼团\", \"拼团\" 103, \"同行打折\", \"同行优惠\" 104, \"同行免单\", \"同行优惠\"","example":null,"creator":null,"children":[]},{"name":"promotion_value","type":"Number","isStruct":false,"desc":"优惠卡面值","example":null,"creator":null,"children":[]},{"name":"real_pay","type":"Number","isStruct":false,"desc":"实际支付价格","example":null,"creator":null,"children":[]},{"name":"reserve_price","type":"Number","isStruct":false,"desc":"预约价格","example":null,"creator":null,"children":[]},{"name":"salesmen","type":"Salesman[]","isStruct":true,"desc":"","example":null,"creator":null,"children":[{"name":"id","type":"Number","isStruct":false,"desc":"销售人员id","example":null,"creator":null,"children":[]}]},{"name":"sku_id","type":"Number","isStruct":false,"desc":"sku id","example":null,"creator":null,"children":[]},{"name":"stage","type":"Number","isStruct":false,"desc":"0 预约，1 订单","example":null,"creator":null,"children":[]},{"name":"technicians","type":"Technician[]","isStruct":true,"desc":"","example":null,"creator":null,"children":[{"name":"assigned","type":"Number","isStruct":false,"desc":"是不是客户指定的技师","example":null,"creator":null,"children":[]},{"name":"id","type":"Number","isStruct":false,"desc":"技师id","example":null,"creator":null,"children":[]}]}]}},{"name":"promotions","type":"Promotion[]","example":"","defaultValue":"","isRequired":"否","desc":"优惠列表","isStruct":true,"structUrl":"/web/apiParamStruct/Promotion","struct":{"name":"Promotion[]","type":"Promotion[]","isStruct":true,"desc":"","example":null,"creator":null,"children":[{"name":"id","type":"Number","isStruct":false,"desc":"优惠id","example":null,"creator":null,"children":[]},{"name":"name","type":"String","isStruct":false,"desc":"优惠名称","example":null,"creator":null,"children":[]},{"name":"stage","type":"Number","isStruct":false,"desc":"0 预约 1订单","example":null,"creator":null,"children":[]},{"name":"type","type":"Number","isStruct":false,"desc":"优惠类型。0, \"无优惠\" 1, \"次卡\" 2, \"折扣值\" 3, \"预付已付款\" 5, \"导入权益次数\" 6, \"赠送权益次数\" 7, \"导入权益折扣\" 8, \"赠送权益折扣\" 11, \"产品折扣（会员特权）\" 21, \"服务折扣（会员特权）\" 30, \"包邮\", \"等级权益包邮\" 31, \"抹零\", \"抹零\" 40, \"手动减价\", \"手动减价\" 51, \"减价优惠券\", \"优惠券\" 52, \"折扣优惠券\", \"优惠券\" 100, \"体验价\", \"体验价优惠\" 101, \"拼团\", \"拼团\" 103, \"同行打折\", \"同行优惠\" 104, \"同行免单\", \"同行优惠\"","example":null,"creator":null,"children":[]},{"name":"value","type":"Number","isStruct":false,"desc":"优惠面值","example":null,"creator":null,"children":[]}]}},{"name":"remark","type":"String","example":"","defaultValue":"","isRequired":"否","desc":"备注","isStruct":false,"structUrl":null,"struct":null},{"name":"reserve_order_no","type":"String","example":"","defaultValue":"","isRequired":"否","desc":"预约单号，如果是预约单转开单的，需要填入该参数，这样当订单保存的时候，对应的预约单会被关闭掉","isStruct":false,"structUrl":null,"struct":null},{"name":"type","type":"Number","example":"","defaultValue":"0","isRequired":"是","desc":"订单类型。0:\"普通\",1,:\"开卡购卡\",2,:\"充值\",3,:\"直接收款\",4:\"台卡\",8:\"产品订单\"。默认是0.","isStruct":false,"structUrl":null,"struct":null}],"responseParams":[{"name":"resp","type":"OrderSaveResp","isRequired":"否","desc":"订单保存响应体","isStruct":true,"structUrl":"/web/meta/OrderSaveResp","struct":{"name":"resp","type":"OrderSaveResp","isNeed":"true","desc":"订单保存响应体","defaultValue":null,"example":"","isStruct":true,"children":[{"name":"yz_uid","type":"Number","isNeed":null,"desc":"订单创建者id","defaultValue":null,"example":null,"isStruct":false,"children":[]},{"name":"order_no","type":"String","isNeed":null,"desc":"订单编号","defaultValue":null,"example":null,"isStruct":false,"children":[]}]}}],"requestDemos":[{"lang":"java","code":"YZClient client = new DefaultYZClient(new Token(\"token\")); //new Sign(appKey, appSecret)\nYouzanMeiOrderCreateParams youzanMeiOrderCreateParams = new YouzanMeiOrderCreateParams();\n\nyouzanMeiOrderCreateParams.setMToken(\"tPEFHHem67xnV0RoeKwB475Qcu-YsRqS8So-1Bo5rVron34cHkFLMU6CH3EjddVSwSrM4ef0NwYrTN0iiF9FgHcs0KWTn8Mr7qIiSa1A6z4\");\nyouzanMeiOrderCreateParams.setOrderItems(\"[{\"item_id\":51891,\"item_type\":1,\"item_name\":\"小气泡\",\"item_alias\":\"2oiyygle0t9yk\",\"goods_id\":439575230,\"sku_id\":36237107,\"num\":1}]\");\nyouzanMeiOrderCreateParams.setRemark(\"1111111\");\nyouzanMeiOrderCreateParams.setType(0L);\nyouzanMeiOrderCreateParams.setDeptId(\"19900722\");\n\nYouzanMeiOrderCreate youzanMeiOrderCreate = new YouzanMeiOrderCreate();\nyouzanMeiOrderCreate.setAPIParams(youzanMeiOrderCreateParams);\nYouzanMeiOrderCreateResult result = client.invoke(youzanMeiOrderCreate);"}],"errorCodes":null,"responseDemo":"{\"response\":{\"order_no\":\"M2018080920194421114745\",\"yz_uid\":721167196}}","errorResponseDemo":"{\"error_response\":{\"msg\":\"抱歉, 服务器开了个小差: \",\"code\":230100000}}"},"name":"create","ids":[10331],"scenarios":"订单创建","version":["3.0.0"],"desc":"订单创建"}